README.md
setup.cfg
setup.py
iimmpact/__init__.py
iimmpact/api_client.py
iimmpact/configuration.py
iimmpact/rest.py
iimmpact.egg-info/PKG-INFO
iimmpact.egg-info/SOURCES.txt
iimmpact.egg-info/dependency_links.txt
iimmpact.egg-info/requires.txt
iimmpact.egg-info/top_level.txt
iimmpact/api/__init__.py
iimmpact/api/authorization_token_api.py
iimmpact/api/callback_url_api.py
iimmpact/api/car_insurance_api.py
iimmpact/api/jpj_records_api.py
iimmpact/api/low_balance_warning_api.py
iimmpact/api/my_account_api.py
iimmpact/api/product_enquiry_api.py
iimmpact/api/services_api.py
iimmpact/api/transaction_history_api.py
iimmpact/models/__init__.py
iimmpact/models/balance_response.py
iimmpact/models/balance_response_data.py
iimmpact/models/balance_statement_response.py
iimmpact/models/balance_statement_response_data.py
iimmpact/models/balance_statement_response_links.py
iimmpact/models/balance_statement_response_meta.py
iimmpact/models/bill_presentment_response.py
iimmpact/models/bill_presentment_response_data.py
iimmpact/models/bill_presentment_response_metadata.py
iimmpact/models/callback_url_response.py
iimmpact/models/callback_url_response_data.py
iimmpact/models/callback_url_response_metadata.py
iimmpact/models/car_insurance_respone.py
iimmpact/models/car_insurance_respone_variant.py
iimmpact/models/change_password_request.py
iimmpact/models/deposit_request.py
iimmpact/models/driving_license_respone.py
iimmpact/models/driving_license_respone_inner.py
iimmpact/models/driving_test_respone.py
iimmpact/models/driving_test_respone_enquiry_test_part1.py
iimmpact/models/empty.py
iimmpact/models/error.py
iimmpact/models/inline_response200.py
iimmpact/models/inline_response2001.py
iimmpact/models/inline_response2002.py
iimmpact/models/inline_response2002_data.py
iimmpact/models/inline_response200_data.py
iimmpact/models/jpj_records_response.py
iimmpact/models/jpj_summons_response.py
iimmpact/models/low_balance_warning_response.py
iimmpact/models/low_balance_warning_response_data.py
iimmpact/models/low_balance_warning_response_metadata.py
iimmpact/models/network_status_response.py
iimmpact/models/network_status_response_data.py
